kodexa/__init__.py
kodexa/assistant/__init__.py
kodexa/assistant/assistant.py
kodexa/connectors/__init__.py
kodexa/connectors/connectors.py
kodexa/dataclasses/__init__.py
kodexa/dataclasses/templates/llm_data_class.j2
kodexa/model/__init__.py
kodexa/model/base.py
kodexa/model/entities/__init__.py
kodexa/model/entities/check_response.py
kodexa/model/entities/product.py
kodexa/model/entities/product_group.py
kodexa/model/entities/product_subscription.py
kodexa/model/objects.py
kodexa/model/utils.py
kodexa/pipeline/__init__.py
kodexa/pipeline/pipeline.py
kodexa/platform/__init__.py
kodexa/platform/client.py
kodexa/platform/interaction.py
kodexa/platform/kodexa.py
kodexa/platform/manifest.py
kodexa/selectors/__init__.py
kodexa/selectors/ast.py
kodexa/selectors/error.py
kodexa/selectors/kodexa-ast-visitor.py
kodexa/selectors/parser.py
kodexa/selectors/resources/KodexaSelector.interp
kodexa/selectors/resources/KodexaSelector.tokens
kodexa/selectors/resources/KodexaSelectorLexer.interp
kodexa/selectors/resources/KodexaSelectorLexer.py
kodexa/selectors/resources/KodexaSelectorLexer.tokens
kodexa/selectors/resources/KodexaSelectorListener.py
kodexa/selectors/resources/KodexaSelectorParser.py
kodexa/selectors/resources/KodexaSelectorVisitor.py
kodexa/selectors/visitor.py
kodexa/spatial/__init__.py
kodexa/spatial/azure_models.py
kodexa/spatial/bbox_common.py
kodexa/spatial/table_form_common.py
kodexa/steps/__init__.py
kodexa/steps/common.py
kodexa/testing/__init__.py
kodexa/testing/test_components.py
kodexa/testing/test_utils.py
kodexa/training/__init__.py
kodexa/training/train_utils.py
kodexa/utils/__init__.py
kodexa-8.0.14958192442.dist-info/LICENSE
kodexa-8.0.14958192442.dist-info/METADATA
kodexa-8.0.14958192442.dist-info/WHEEL
kodexa-8.0.14958192442.dist-info/RECORD
