Metadata-Version: 2.3
Name: kodexa
Version: 8.0.14958192442
Summary: Python SDK for the Kodexa Platform
Author: Austin Redenbaugh
Author-email: austin@kodexa.com
Requires-Python: >=3.11,<3.14
Classifier: Development Status :: 5 - Production/Stable
Classifier: Intended Audience :: Developers
Classifier: License :: OSI Approved :: Apache Software License
Classifier: Programming Language :: Python :: 3
Classifier: Programming Language :: Python :: 3.11
Classifier: Programming Language :: Python :: 3.12
Classifier: Programming Language :: Python :: 3.13
Classifier: Topic :: Software Development :: Libraries
Requires-Dist: addict (>=2.4.0,<3.0.0)
Requires-Dist: antlr4-python3-runtime (>=4.13.2,<5.0.0)
Requires-Dist: appdirs (>=1.4.4,<2.0.0)
Requires-Dist: better-exceptions (>=0.3.3,<0.4.0)
Requires-Dist: certifi (>=2025.0.0,<2026.0.0)
Requires-Dist: chevron (>=0.14.0,<0.15.0)
Requires-Dist: deepdiff (>=8.0.1,<9.0.0)
Requires-Dist: kodexa-document (>=8.0.0,<9.0.0)
Requires-Dist: msgpack (>=1.0.6,<2.0.0)
Requires-Dist: ply (>=3.11,<4.0)
Requires-Dist: pydantic (>=2.5.3,<3.0.0)
Requires-Dist: pydantic-yaml (>=1.0.0,<2.0.0)
Requires-Dist: pyfunctional (==1.5.0)
Requires-Dist: python-dateutil (>=2.8.2,<3.0.0)
Requires-Dist: pyyaml (>=6.0,<7.0)
Requires-Dist: requests (>=2.28.1,<3.0.0)
Requires-Dist: semver (>=3.0.1,<4.0.0)
Requires-Dist: simpleeval (>=1.0.0,<2.0.0)
Requires-Dist: urllib3 (>=2.0.0,<3.0.0)
